{
    "schema":{
        "fields":[
            {
                "name":"genre",
                "type":"string"
            },
            {
                "name":"movies_count",
                "type":"integer"
            }
        ],
        "pandas_version":"0.20.0"
    },
    "data":[
        {
            "genre":"Drama",
            "movies_count":20244
        },
        {
            "genre":"Comedy",
            "movies_count":13176
        },
        {
            "genre":"Thriller",
            "movies_count":7619
        },
        {
            "genre":"Romance",
            "movies_count":6730
        },
        {
            "genre":"Action",
            "movies_count":6592
        },
        {
            "genre":"Horror",
            "movies_count":4671
        },
        {
            "genre":"Crime",
            "movies_count":4304
        },
        {
            "genre":"Documentary",
            "movies_count":3930
        },
        {
            "genre":"Adventure",
            "movies_count":3490
        },
        {
            "genre":"Science Fiction",
            "movies_count":3044
        },
        {
            "genre":"Family",
            "movies_count":2767
        },
        {
            "genre":"Mystery",
            "movies_count":2464
        },
        {
            "genre":null,
            "movies_count":2442
        },
        {
            "genre":"Fantasy",
            "movies_count":2309
        },
        {
            "genre":"Animation",
            "movies_count":1931
        },
        {
            "genre":"Foreign",
            "movies_count":1619
        },
        {
            "genre":"Music",
            "movies_count":1597
        },
        {
            "genre":"History",
            "movies_count":1398
        },
        {
            "genre":"War",
            "movies_count":1322
        },
        {
            "genre":"Western",
            "movies_count":1042
        },
        {
            "genre":"TV Movie",
            "movies_count":766
        },
        {
            "genre":"Aniplex",
            "movies_count":1
        },
        {
            "genre":"BROSTA TV",
            "movies_count":1
        },
        {
            "genre":"Carousel Productions",
            "movies_count":1
        },
        {
            "genre":"GoHands",
            "movies_count":1
        },
        {
            "genre":"Mardock Scramble Production Committee",
            "movies_count":1
        },
        {
            "genre":"Odyssey Media",
            "movies_count":1
        },
        {
            "genre":"Pulser Productions",
            "movies_count":1
        },
        {
            "genre":"Rogue State",
            "movies_count":1
        },
        {
            "genre":"Sentai Filmworks",
            "movies_count":1
        },
        {
            "genre":"Telescene Film Group Productions",
            "movies_count":1
        },
        {
            "genre":"The Cartel",
            "movies_count":1
        },
        {
            "genre":"Vision View Entertainment",
            "movies_count":1
        }
    ]
}